slsdebugger/__init__.py
slsdebugger/_version.py
slsdebugger/compat.py
slsdebugger/constants.py
slsdebugger/handler.py
slsdebugger/timeout.py
slsdebugger/config/__init__.py
slsdebugger/config/config_metadata.py
slsdebugger/config/config_names.py
slsdebugger/config/config_provider.py
slsdebugger/debug/__init__.py
slsdebugger/debug/bridge.py
slsdebugger/log/__init__.py
slsdebugger/log/logger.py
slsdebugger/wrappers/__init__.py
slsdebugger/wrappers/lambda_wrapper.py
slsdebugger/wrappers/wrapper_factory.py
slsdebugger-0.0.9.dist-info/LICENSE
slsdebugger-0.0.9.dist-info/METADATA
slsdebugger-0.0.9.dist-info/WHEEL
slsdebugger-0.0.9.dist-info/top_level.txt
slsdebugger-0.0.9.dist-info/zip-safe
slsdebugger-0.0.9.dist-info/RECORD
