Metadata-Version: 2.1
Name: slsdebugger
Version: 0.0.9
Summary: Serverless Debugger Python
Home-page: https://github.com/serverlessdebugger/serverlessdebugger-agent-python
Author: Thundra
Author-email: python@thundra.io
Classifier: Development Status :: 5 - Production/Stable
Classifier: Intended Audience :: Developers
Classifier: License :: OSI Approved :: Apache Software License
Classifier: Programming Language :: Python
Classifier: Programming Language :: Python :: 3
Classifier: Programming Language :: Python :: 3.6
Classifier: Programming Language :: Python :: 3.7
Classifier: Programming Language :: Python :: 3.8
Classifier: Programming Language :: Python :: 3.9
Requires-Python: !=2.7, !=3.0.*, !=3.1.*, !=3.2.*, !=3.3.*, !=3.4.*, !=3.5.*
License-File: LICENSE
Requires-Dist: websocket-client
Requires-Dist: ptvsd
